ProxyRipper/ProxyRipper.py
ProxyRipper/__init__.py
ProxyRipper/api/__init__.py
ProxyRipper/api/cache_api.py
ProxyRipper/api/geonode_api.py
ProxyRipper/utils/ProxyEngine.py
ProxyRipper/utils/__init__.py
ProxyRipper/utils/printer.py
ProxyRipper/utils/proxycheck.py
ProxyRipper/utils/scrap.py
ProxyRipper-1.1.3.dist-info/LICENCE
ProxyRipper-1.1.3.dist-info/METADATA
ProxyRipper-1.1.3.dist-info/WHEEL
ProxyRipper-1.1.3.dist-info/entry_points.txt
ProxyRipper-1.1.3.dist-info/top_level.txt
ProxyRipper-1.1.3.dist-info/RECORD
